[
  {
    "question": "What is the examination format?",
    "answer": "Depends on the subject:\n- Written examinations\n- Practical assessments\n- Coursework and assignments\n- Presentations and projects\n- Online assessments"
  },
  {
    "question": "How do I check my exam results?",
    "answer": "Results are available through the student portal 2-3 weeks after examinations."
  },
  {
    "question": "What is the minimum passing grade?",
    "answer": "Generally, a minimum of 40% is required to pass most subjects, but this varies by programme."
  },
  {
    "question": "Can I appeal my exam results?",
    "answer": "Yes, result appeals can be submitted within 2 weeks of result publication through the academic office."
  },
  {
    "question": "What happens if I fail a subject?",
    "answer": "You can retake the subject in the following semester. Consult your academic advisor for guidance."
  },
  {
    "question": "How is the GPA calculated?",
    "answer": "GPA is calculated based on credit hours and grade points. The grading scale ranges from A+ (4.0) to F (0.0)."
  }
]
